<?xml version="1.0" encoding="UTF-8"?>
<Node>
    <Option>
      <ManualPwrLvl Description="Manual Set Power Level" Control="CheckBox">0</ManualPwrLvl>
      <Band_24G>
          <Ant1st Description="Channel 0 enable" Control="CheckBox">1</Ant1st>
          <RfSwitchAnt1st Description="Outer Customer Rf Switch Ant1st">0</RfSwitchAnt1st>
          <Ant2nd Description="Channel 1 enable" Control="CheckBox">0</Ant2nd>
          <RfSwitchAnt2nd Description="Outer Customer Rf Switch Ant2nd">0</RfSwitchAnt2nd>
          <Wlan11b Description="802.11b measurement switcher, if checkbox is enabled, measurement will be performed or not">
            <BW_20M Description="802.11b bandwidth 20M measurement switcher, if checkbox is enabled, measurement will be performed or not" Control="CheckBox">1</BW_20M>
          </Wlan11b>
          <Wlan11g Description="802.11g measurement switcher, if checkbox is enabled, measurement will be performed or not">
            <BW_20M Description="802.11g bandwidth 20M measurement switcher, if checkbox is enabled, measurement will be performed or not" Control="CheckBox">1</BW_20M>
          </Wlan11g>
          <Wlan11n Description="802.11n measurement switcher, if checkbox is enabled, measurement will be performed or not" >
            <BW_20M Description="802.11n bandwidth 20M measurement switcher, if checkbox is enabled, measurement will be performed or not" Control="CheckBox">1</BW_20M>
            <BW_40M Description="802.11n bandwidth 40M measurement switcher, if checkbox is enabled, measurement will be performed or not" Control="CheckBox">1</BW_40M>
          </Wlan11n>
            <Wlan11ac Description="802.11ac measurement switcher, if checkbox is enabled, measurement will be performed or not">
                <BW_20M Description="bandwidth 20M measurement switcher, if checkbox is enabled, measurement will be performed or not" Control="CheckBox">1</BW_20M>
                <BW_40M Description="bandwidth 40M measurement switcher, if checkbox is enabled, measurement will be performed or not" Control="CheckBox">1</BW_40M>
            </Wlan11ac>
          <Wlan11ax Description="802.11ax measurement switcher, if checkbox is enabled, measurement will be performed or not" >
            <BW_20M Description="802.11ax bandwidth 20M measurement switcher, if checkbox is enabled, measurement will be performed or not" Control="CheckBox">1</BW_20M>
            <BW_40M Description="802.11ax bandwidth 40M measurement switcher, if checkbox is enabled, measurement will be performed or not" Control="CheckBox">1</BW_40M>
          </Wlan11ax>
      </Band_24G>
      <Band_50G>
        <Ant1st Description="Channel 0 enable" Control="CheckBox">1</Ant1st>
        <RfSwitchAnt1st Description="Outer Customer Rf Switch Ant1st">0</RfSwitchAnt1st>
        <Ant2nd Description="Channel 1 enable" Control="CheckBox">0</Ant2nd>
        <RfSwitchAnt2nd Description="Outer Customer Rf Switch Ant2nd">0</RfSwitchAnt2nd>        
        <Wlan11n Description="802.11n measurement switcher, if checkbox is enabled, measurement will be performed or not">
          <BW_20M Description="802.11n bandwidth 20M measurement switcher, if checkbox is enabled, measurement will be performed or not" Control="CheckBox">1</BW_20M>
          <BW_40M Description="802.11n bandwidth 40M measurement switcher, if checkbox is enabled, measurement will be performed or not" Control="CheckBox">1</BW_40M>
        </Wlan11n>
        <Wlan11ac Description="802.11ac measurement switcher, if checkbox is enabled, measurement will be performed or not">
          <BW_20M Description="bandwidth 20M measurement switcher, if checkbox is enabled, measurement will be performed or not" Control="CheckBox">1</BW_20M>
          <BW_40M Description="bandwidth 40M measurement switcher, if checkbox is enabled, measurement will be performed or not" Control="CheckBox">1</BW_40M>
          <BW_80M Description="bandwidth 80M measurement switcher, if checkbox is enabled, measurement will be performed or not" Control="CheckBox">1</BW_80M>
        </Wlan11ac>
        <Wlan11a Description="802.11a measurement switcher, if checkbox is enabled, measurement will be performed or not">
          <BW_20M Description="bandwidth 20M measurement switcher, if checkbox is enabled, measurement will be performed or not" Control="CheckBox">1</BW_20M>
        </Wlan11a>
        <Wlan11ax Description="802.11ax measurement switcher, if checkbox is enabled, measurement will be performed or not" >
          <BW_20M Description="802.11ax bandwidth 20M measurement switcher, if checkbox is enabled, measurement will be performed or not" Control="CheckBox">1</BW_20M>
          <BW_40M Description="802.11ax bandwidth 40M measurement switcher, if checkbox is enabled, measurement will be performed or not" Control="CheckBox">1</BW_40M>
          <BW_80M Description="802.11ax bandwidth 80M measurement switcher, if checkbox is enabled, measurement will be performed or not" Control="CheckBox">1</BW_80M>
          <!--BW_160M Property="ReadOnly" Description="802.11ax bandwidth 160M measurement switcher, if checkbox is enabled, measurement will be performed or not" Control="CheckBox">0</BW_160M-->          
        </Wlan11ax>        
      </Band_50G>
    </Option>
    <Param>
      <Common>
        <AvgCount Description="Average Count for Measurements">3</AvgCount>
        <TxSleep Description="delay for TX Measurements, unit:ms">10</TxSleep>
      </Common>
      <Band_24G>
        <Wlan11b Description="802.11b/g/n Band" Control="Group">
          <BW_20M Control="Group">
            <GroupCount>1</GroupCount>
            <Group1>
              <CenChan Description="Center channel 1~13 is available">1,7,13</CenChan>
              <Modulation Description="Different modulation type with different data rate, the matching map is DSSS-1:1.0Mbps,DSSS-2:2.0Mbps,CCK-5.5:5.5Mbps,CCK-11:11.0Mbps" Control="ComboBox" Elements="DSSS-1,DSSS-2,CCK-5.5,CCK-11">CCK-11</Modulation>
              <RXLVL Description="Rx level for per measurement. Unit:dBm">
                <DSSS-1>-80</DSSS-1>
                <DSSS-2>-80</DSSS-2>
                <CCK-5.5>-80</CCK-5.5>
                <CCK-11>-76</CCK-11>
              </RXLVL>
              <PacketCount Description="Total packets count for RX configuration!">200</PacketCount>
              <RefLVL Description="Reference level for tx measure. Unit:dBm">20</RefLVL>
              <ChanCoding Description="Channel coding type selected: BCC, LDPC"  Control="ComboBox" Elements="0:BCC, 1:LDPC">0</ChanCoding>
              <TestItem>
                <TXP Description="Transmit power level" Control="CheckBox">1</TXP>
                <TCFT Description="Transmit center frequency tolerance" Control="CheckBox">1</TCFT>
                <IQoffset Description="MODulation I/Q offset" Control="CheckBox">0</IQoffset>                
                <EVM Description="Error vector magnitude" Control="CheckBox">1</EVM>
                <SPECMASK Description="Transmit spectrum mask" Control="CheckBox">1</SPECMASK>
                <PER Description="Receiver sensitivity" Control="CheckBox">1</PER>
                <RSSI Description="Received Signal Strength Indicator" Control="CheckBox">0</RSSI>   
                <SNR Description="Signal to Noise Ratio" Control="CheckBox">1</SNR>       
              </TestItem>
            </Group1>
          </BW_20M>
          <Specification Description="Configure the test tolerance and specification">
            <TXP Description="TX Power, Unit: dBm">
              <DSSS-1>8,23</DSSS-1>
              <DSSS-2>8,23</DSSS-2>
              <CCK-5.5>8,23</CCK-5.5>
              <CCK-11>8,23</CCK-11>
            </TXP>
            <TXPant2nd Description="TX Power, Unit: dBm">
              <DSSS-1>8,23</DSSS-1>
              <DSSS-2>8,23</DSSS-2>
              <CCK-5.5>8,23</CCK-5.5>
              <CCK-11>8,23</CCK-11>
            </TXPant2nd>
            <EVM Description="Error Vector Magnitude, Unit: %">
              <DSSS-1>35</DSSS-1>
              <DSSS-2>35</DSSS-2>
              <CCK-5.5>35</CCK-5.5>
              <CCK-11>35</CCK-11>
            </EVM>
            <SPECMASK Description="Transmit spectrum mask margin">0,0,0,0</SPECMASK>
            <TCFT Description="Transmit Center Frequency Tolerance, Unit: PPM">-15,15</TCFT>
            <IQoffset Description="MODulation I/Q offset, Unit: db">-100,-15</IQoffset>
            <PER>8</PER>
            <RSSI Description="Received Signal Strength Indicator.RXLVL+/-Limit">-4,4</RSSI>           
	    <SNR>10</SNR>
          </Specification>
        </Wlan11b>
        <Wlan11g Description="802.11g Band" Control="Group">
          <BW_20M Control="Group">
            <GroupCount>1</GroupCount>
            <Group1>
              <CenChan Description="Center channel 1~13 is available">1,7,13</CenChan>
              <Modulation Control="ComboBox" Elements="OFDM-6,OFDM-9,OFDM-12,OFDM-18,OFDM-24,OFDM-36,OFDM-48,OFDM-54">OFDM-54</Modulation>
              <RXLVL Description="Rx level for per measurement. Unit:dBm">
                <OFDM-6>-82</OFDM-6>
                <OFDM-9>-81</OFDM-9>
                <OFDM-12>-79</OFDM-12>
                <OFDM-18>-77</OFDM-18>
                <OFDM-24>-74</OFDM-24>
                <OFDM-36>-70</OFDM-36>
                <OFDM-48>-66</OFDM-48>
                <OFDM-54>-65</OFDM-54>
              </RXLVL>
              <PacketCount Description="Total packets count for RX configuration!">200</PacketCount>
              <RefLVL Description="Reference level for tx measure. Unit:dBm">20</RefLVL>
              <ChanCoding Description="Channel coding type selected: BCC, LDPC"  Control="ComboBox" Elements="0:BCC, 1:LDPC">0</ChanCoding>
              <TestItem>
                <TXP Description="Transmit power level" Control="CheckBox">1</TXP>
                <TCFT Description="Transmit center frequency tolerance" Control="CheckBox">1</TCFT>
                <IQoffset Description="MODulation I/Q offset" Control="CheckBox">0</IQoffset>                
                <EVM Description="Error vector magnitude" Control="CheckBox">1</EVM>
                <SPECMASK Description="Transmit spectrum mask" Control="CheckBox">1</SPECMASK>
                <PER Description="Receiver sensitivity" Control="CheckBox">1</PER>
                <RSSI Description="Received Signal Strength Indicator" Control="CheckBox">0</RSSI>  
                <SNR Description="Signal to Noise Ratio" Control="CheckBox">1</SNR>            
              </TestItem>
            </Group1>
          </BW_20M>
          <Specification Description="Configure the test tolerance and specification">
            <TXP Description="TX Power, Unit: dBm">
              <OFDM-6>8,23</OFDM-6>
              <OFDM-9>8,23</OFDM-9>
              <OFDM-12>8,23</OFDM-12>
              <OFDM-18>8,23</OFDM-18>
              <OFDM-24>8,23</OFDM-24>
              <OFDM-36>8,23</OFDM-36>
              <OFDM-48>8,23</OFDM-48>
              <OFDM-54>8,23</OFDM-54>
            </TXP>
            <TXPant2nd Description="TX Power, Unit: dBm">
              <OFDM-6>8,23</OFDM-6>
              <OFDM-9>8,23</OFDM-9>
              <OFDM-12>8,23</OFDM-12>
              <OFDM-18>8,23</OFDM-18>
              <OFDM-24>8,23</OFDM-24>
              <OFDM-36>8,23</OFDM-36>
              <OFDM-48>8,23</OFDM-48>
              <OFDM-54>8,23</OFDM-54>
            </TXPant2nd>            
            <TCFT Description="Transmit Center Freq Tolerance, Unit: PPM">-15,15</TCFT>
            <IQoffset Description="MODulation I/Q offset, Unit: db">-100,-15</IQoffset>
            <EVM Description="Error Vector Magnitude, Unit: %">
              <OFDM-6>-5</OFDM-6>
              <OFDM-9>-8</OFDM-9>
              <OFDM-12>-10</OFDM-12>
              <OFDM-18>-13</OFDM-18>
              <OFDM-24>-16</OFDM-24>
              <OFDM-36>-19</OFDM-36>
              <OFDM-48>-22</OFDM-48>
              <OFDM-54>-25</OFDM-54>
            </EVM>
            <SPECMASK Description="Transmit spectrum mask margin">0,0,0,0,0,0,0,0</SPECMASK>
            <PER>10</PER>
            <RSSI Description="Received Signal Strength Indicator.RXLVL+/-Limit">-4,4</RSSI>            
	    <SNR>10</SNR>
          </Specification>
        </Wlan11g>
        <Wlan11n Description="802.11n Band" Control="Group">
          <BW_20M Control="Group">
            <GroupCount>1</GroupCount>
            <Group1>
              <CenChan Description="Center channel 1~13 is available">1,7,13</CenChan>
              <Modulation Control="ComboBox" Elements="MCS-0,MCS-1,MCS-2,MCS-3,MCS-4,MCS-5,MCS-6,MCS-7">MCS-6</Modulation>
              <RXLVL Description="Rx level for per measurement. Unit:dBm">
                <MCS-0>-82</MCS-0>
                <MCS-1>-79</MCS-1>
                <MCS-2>-77</MCS-2>
                <MCS-3>-74</MCS-3>
                <MCS-4>-70</MCS-4>
                <MCS-5>-66</MCS-5>
                <MCS-6>-65</MCS-6>
                <MCS-7>-64</MCS-7>
              </RXLVL>
              <PacketCount Description="Total packets count for RX configuration!">200</PacketCount>
              <RefLVL Description="Reference level for tx measure. Unit:dBm">20</RefLVL>
              <ChanCoding Description="Channel coding type selected: BCC, LDPC"  Control="ComboBox" Elements="0:BCC, 1:LDPC">0</ChanCoding>
              <TestItem>
                <TXP Description="Transmit power level" Control="CheckBox">1</TXP>
                <TCFT Description="Transmit center frequency tolerance" Control="CheckBox">1</TCFT>
                <IQoffset Description="MODulation I/Q offset" Control="CheckBox">0</IQoffset>                
                <EVM Description="Error vector magnitude" Control="CheckBox">1</EVM>
                <SPECMASK Description="Transmit spectrum mask" Control="CheckBox">1</SPECMASK>
                <PER Description="Receiver sensitivity" Control="CheckBox">1</PER>
                <RSSI Description="Received Signal Strength Indicator" Control="CheckBox">0</RSSI> 
                <SNR Description="Signal to Noise Ratio" Control="CheckBox">1</SNR>           
              </TestItem>
            </Group1>
          </BW_20M>
          <BW_40M Control="Group">
            <GroupCount>1</GroupCount>
            <Group1>
              <CenChan Description="Center channel 3~11 is available">3,7,11</CenChan>
              <PriChan Description="Primary channel position. 1:+10M,-1:-10M" Control="ComboBox" Elements="1,-1">1</PriChan>
              <Modulation Control="ComboBox" Elements="MCS-0,MCS-1,MCS-2,MCS-3,MCS-4,MCS-5,MCS-6,MCS-7">MCS-7</Modulation>
              <RXLVL Description="Rx level for per measurement. Unit:dBm">
                <MCS-0>-79</MCS-0>
                <MCS-1>-76</MCS-1>
                <MCS-2>-74</MCS-2>
                <MCS-3>-71</MCS-3>
                <MCS-4>-67</MCS-4>
                <MCS-5>-63</MCS-5>
                <MCS-6>-62</MCS-6>
                <MCS-7>-61</MCS-7>
              </RXLVL>
              <PacketCount Description="Total packets count for RX configuration!">200</PacketCount>
              <RefLVL Description="Reference level for tx measure. Unit:dBm">20</RefLVL>
              <ChanCoding Description="Channel coding type selected: BCC, LDPC"  Control="ComboBox" Elements="0:BCC, 1:LDPC">0</ChanCoding>
              <SBW Property="ReadOnly" Description="Signal Bandwidth. 0:20M, 1:40M, 2:80M"  Control="ComboBox" Elements="0,1">1</SBW>
              <TestItem>
                <TXP Description="Transmit power level" Control="CheckBox">1</TXP>
                <TCFT Description="Transmit center frequency tolerance" Control="CheckBox">1</TCFT>
                <IQoffset Description="MODulation I/Q offset" Control="CheckBox">0</IQoffset>                
                <EVM Description="Error vector magnitude" Control="CheckBox">1</EVM>
                <SPECMASK Description="Transmit spectrum mask" Control="CheckBox">1</SPECMASK>
                <PER Description="Receiver sensitivity" Control="CheckBox">1</PER>
                <RSSI Description="Received Signal Strength Indicator" Control="CheckBox">0</RSSI>   
                <SNR Description="Signal to Noise Ratio" Control="CheckBox">1</SNR>            
              </TestItem>
            </Group1>
          </BW_40M>
          <Specification Description="Configure the test tolerance and specification">
            <TXP Description="TX Power, Unit: dBm">
              <MCS-0>8,23</MCS-0>
              <MCS-1>8,23</MCS-1>
              <MCS-2>8,23</MCS-2>
              <MCS-3>8,23</MCS-3>
              <MCS-4>8,23</MCS-4>
              <MCS-5>8,23</MCS-5>
              <MCS-6>8,23</MCS-6>
              <MCS-7>8,23</MCS-7>
            </TXP>
            <TXPant2nd Description="TX Power, Unit: dBm">
              <MCS-0>8,23</MCS-0>
              <MCS-1>8,23</MCS-1>
              <MCS-2>8,23</MCS-2>
              <MCS-3>8,23</MCS-3>
              <MCS-4>8,23</MCS-4>
              <MCS-5>8,23</MCS-5>
              <MCS-6>8,23</MCS-6>
              <MCS-7>8,23</MCS-7>
            </TXPant2nd>            
            <EVM Description="Error Vector Magnitude, Unit: %">
              <MCS-0>-5</MCS-0>
              <MCS-1>-10</MCS-1>
              <MCS-2>-13</MCS-2>
              <MCS-3>-16</MCS-3>
              <MCS-4>-19</MCS-4>
              <MCS-5>-22</MCS-5>
              <MCS-6>-25</MCS-6>
              <MCS-7>-28</MCS-7>
            </EVM>
            <SPECMASK Description="Transmit spectrum mask margin">0,0,0,0,0,0,0,0</SPECMASK>
            <TCFT Description="Transmit Center Frequency Tolerance, Unit: PPM">-15,15</TCFT>
            <IQoffset Description="MODulation I/Q offset, Unit: db">-100,-20</IQoffset>
            <PER>10</PER>
            <RSSI Description="Received Signal Strength Indicator.RXLVL+/-Limit">-4,4</RSSI>
            <SNR>10</SNR>
          </Specification>
        </Wlan11n>
            <Wlan11ac Description="802.11ac Band" Control="Group">
                <BW_20M Control="Group">
                    <GroupCount>1</GroupCount>
                    <Group1>
                        <CenChan Description="Center channel 1~13 is available">1,7,13</CenChan>
                        <Modulation Control="ComboBox" Elements="MCS0_1SS,MCS1_1SS,MCS2_1SS,MCS3_1SS,MCS4_1SS,MCS5_1SS,MCS6_1SS,MCS7_1SS,MCS8_1SS">MCS7_1SS</Modulation>
                        <RXLVL Description="Rx level for per measurement. Unit:dBm">
                            <MCS0_1SS>-82</MCS0_1SS>
                            <MCS1_1SS>-79</MCS1_1SS>
                            <MCS2_1SS>-77</MCS2_1SS>
                            <MCS3_1SS>-74</MCS3_1SS>
                            <MCS4_1SS>-70</MCS4_1SS>
                            <MCS5_1SS>-66</MCS5_1SS>
                            <MCS6_1SS>-65</MCS6_1SS>
                            <MCS7_1SS>-64</MCS7_1SS>
                            <MCS8_1SS>-59</MCS8_1SS>
                            <MCS9_1SS>-57</MCS9_1SS>
                        </RXLVL>
                        <PacketCount Description="Total packets count for RX configuration!">200</PacketCount>
                        <RefLVL Description="Reference level for tx measure. Unit:dBm">20</RefLVL>
                        <ChanCoding Description="Channel coding type selected: BCC, LDPC"  Control="ComboBox" Elements="0:BCC, 1:LDPC">0</ChanCoding>
                        <TestItem>
                            <TXP Description="Transmit power level" Control="CheckBox">1</TXP>
                            <TCFT Description="Transmit center frequency tolerance" Control="CheckBox">1</TCFT>
                            <IQoffset Description="MODulation I/Q offset" Control="CheckBox">0</IQoffset>
                            <EVM Description="Error vector magnitude" Control="CheckBox">1</EVM>
                            <SPECMASK Description="Transmit spectrum mask" Control="CheckBox">1</SPECMASK>
                            <PER Description="Receiver sensitivity" Control="CheckBox">1</PER>
                            <RSSI Description="Received Signal Strength Indicator" Control="CheckBox">0</RSSI>
                            <SNR Description="Signal to Noise Ratio" Control="CheckBox">1</SNR>
                        </TestItem>
                    </Group1>
                </BW_20M>
                <BW_40M Control="Group">
                    <GroupCount>1</GroupCount>
                    <Group1>
                        <CenChan Description="Center channel 3~11 is available">3,7,11</CenChan>
                        <PriChan Description="Primary channel position. 1:+10M,0:0,-1:-10M" Control="ComboBox" Elements="1,-1">1</PriChan>
                        <Modulation Control="ComboBox" Elements="MCS0_1SS,MCS1_1SS,MCS2_1SS,MCS3_1SS,MCS4_1SS,MCS5_1SS,MCS6_1SS,MCS7_1SS,MCS8_1SS,MCS9_1SS">MCS8_1SS</Modulation>
                        <RXLVL Description="Rx level for per measurement. Unit:dBm">
                            <MCS0_1SS>-79</MCS0_1SS>
                            <MCS1_1SS>-76</MCS1_1SS>
                            <MCS2_1SS>-74</MCS2_1SS>
                            <MCS3_1SS>-71</MCS3_1SS>
                            <MCS4_1SS>-67</MCS4_1SS>
                            <MCS5_1SS>-63</MCS5_1SS>
                            <MCS6_1SS>-62</MCS6_1SS>
                            <MCS7_1SS>-61</MCS7_1SS>
                            <MCS8_1SS>-56</MCS8_1SS>
                            <MCS9_1SS>-54</MCS9_1SS>
                        </RXLVL>
                        <PacketCount Description="Total packets count for RX configuration!">200</PacketCount>
                        <RefLVL Description="Reference level for tx measure. Unit:dBm">20</RefLVL>
                        <ChanCoding Description="Channel coding type selected: BCC, LDPC"  Control="ComboBox" Elements="0:BCC, 1:LDPC">0</ChanCoding>
                        <SBW Description="Signal Bandwidth. 0:20M, 1:40M"  Control="ComboBox" Elements="0,1">1</SBW>
                        <TestItem>
                            <TXP Description="Transmit power level" Control="CheckBox">1</TXP>
                            <TCFT Description="Transmit center frequency tolerance" Control="CheckBox">1</TCFT>
                            <IQoffset Description="MODulation I/Q offset" Control="CheckBox">0</IQoffset>
                            <EVM Description="Error vector magnitude" Control="CheckBox">1</EVM>
                            <SPECMASK Description="Transmit spectrum mask" Control="CheckBox">1</SPECMASK>
                            <PER Description="Receiver sensitivity" Control="CheckBox">1</PER>
                            <RSSI Description="Received Signal Strength Indicator" Control="CheckBox">0</RSSI>
                            <SNR Description="Signal to Noise Ratio" Control="CheckBox">1</SNR>
                        </TestItem>
                    </Group1>
                </BW_40M> 
                <Specification Description="Configure the test tolerance and specification">
                    <TXP Description="TX Power, Unit: dBm">
                      <MCS0_1SS>8,23</MCS0_1SS>
                      <MCS1_1SS>8,23</MCS1_1SS>
                      <MCS2_1SS>8,23</MCS2_1SS>
                      <MCS3_1SS>8,23</MCS3_1SS>
                      <MCS4_1SS>8,23</MCS4_1SS>
                      <MCS5_1SS>8,23</MCS5_1SS>
                      <MCS6_1SS>8,23</MCS6_1SS>
                      <MCS7_1SS>8,23</MCS7_1SS>
                      <MCS8_1SS>8,23</MCS8_1SS>
                      <MCS9_1SS>8,23</MCS9_1SS>
                    </TXP>
                    <TXPant2nd Description="TX Power, Unit: dBm">
                      <MCS0_1SS>8,23</MCS0_1SS>
                      <MCS1_1SS>8,23</MCS1_1SS>
                      <MCS2_1SS>8,23</MCS2_1SS>
                      <MCS3_1SS>8,23</MCS3_1SS>
                      <MCS4_1SS>8,23</MCS4_1SS>
                      <MCS5_1SS>8,23</MCS5_1SS>
                      <MCS6_1SS>8,23</MCS6_1SS>
                      <MCS7_1SS>8,23</MCS7_1SS>
                      <MCS8_1SS>8,23</MCS8_1SS>
                      <MCS9_1SS>8,23</MCS9_1SS>
                    </TXPant2nd>
                    <EVM Description="Error Vector Magnitude, Unit: %">
                        <MCS0_1SS>-5</MCS0_1SS>
                        <MCS1_1SS>-10</MCS1_1SS>
                        <MCS2_1SS>-13</MCS2_1SS>
                        <MCS3_1SS>-16</MCS3_1SS>
                        <MCS4_1SS>-19</MCS4_1SS>
                        <MCS5_1SS>-22</MCS5_1SS>
                        <MCS6_1SS>-25</MCS6_1SS>
                        <MCS7_1SS>-28</MCS7_1SS>
                        <MCS8_1SS>-30</MCS8_1SS>
                        <MCS9_1SS>-32</MCS9_1SS>
                    </EVM>
                    <SPECMASK Description="Transmit spectrum mask margin">0,0,0,0,0,0,0,0</SPECMASK>
                    <TCFT Description="Transmit Center Frequency Tolerance, Unit: PPM">-15,15</TCFT>
                    <IQoffset Description="MODulation I/Q offset, Unit: db">-100,-24</IQoffset>
                    <PER>10</PER>
                    <RSSI Description="Received Signal Strength Indicator.RXLVL+/-Limit">-4,4</RSSI>
                    <SNR>10</SNR>
                </Specification>
            </Wlan11ac>
        <Wlan11ax Description="802.11ax Band" Control="Group">
          <BW_20M Control="Group">
            <GroupCount>1</GroupCount>
            <Group1>
              <CenChan Description="Center channel 1~13 is available">1,7,13</CenChan>
              <Modulation Control="ComboBox" Elements="HE_MCS0_1SS,HE_MCS1_1SS,HE_MCS2_1SS,HE_MCS3_1SS,HE_MCS4_1SS,HE_MCS5_1SS,HE_MCS6_1SS,HE_MCS7_1SS,HE_MCS8_1SS,HE_MCS9_1SS,HE_MCS10_1SS,HE_MCS11_1SS">HE_MCS10_1SS</Modulation>
              <RXLVL Description="Rx level for per measurement. Unit:dBm">
                <HE_MCS0_1SS>-82</HE_MCS0_1SS>
                <HE_MCS1_1SS>-79</HE_MCS1_1SS>
                <HE_MCS2_1SS>-77</HE_MCS2_1SS>
                <HE_MCS3_1SS>-74</HE_MCS3_1SS>
                <HE_MCS4_1SS>-70</HE_MCS4_1SS>
                <HE_MCS5_1SS>-66</HE_MCS5_1SS>
                <HE_MCS6_1SS>-65</HE_MCS6_1SS>
                <HE_MCS7_1SS>-64</HE_MCS7_1SS>
                <HE_MCS8_1SS>-59</HE_MCS8_1SS>
                <HE_MCS9_1SS>-57</HE_MCS9_1SS>
                <HE_MCS10_1SS>-54</HE_MCS10_1SS>
                <HE_MCS11_1SS>-52</HE_MCS11_1SS>
              </RXLVL>
              <PacketCount Description="Total packets count for RX configuration!">200</PacketCount>
              <RefLVL Description="Reference level for tx measure. Unit:dBm">20</RefLVL>
              <ChanCoding Description="Channel coding type selected: BCC, LDPC"  Control="ComboBox" Elements="0:BCC, 1:LDPC">1</ChanCoding>
              <LtfModeGi Description="Set He Ltf Mode, Guard Interval"  Control="ComboBox" Elements="0:(3.2us 1x)-Gi:1(0.8us),1:(6.4us 2x)-Gi:1(0.8us),1:(6.4us 2x)-Gi:2(1.6us),2:(12.8us 4x)-Gi:1(0.8us),2:(12.8us 4x)-Gi:3(3.2us)">0:(3.2us 1x)-Gi:1(0.8us)</LtfModeGi>
              <RuSize Property ="InVisible" Description="Set Ru Size"  Control="ComboBox" Elements="26:26-RU,52:52-RU,106:106-RU,242:242-RU,484:484-RU,996:996-RU">26:26-RU</RuSize>
              <TestItem>
                <TXP Description="Transmit power level" Control="CheckBox">1</TXP>
                <TCFT Description="Transmit center frequency tolerance" Control="CheckBox">1</TCFT>
                <IQoffset Description="MODulation I/Q offset" Control="CheckBox">0</IQoffset>                
                <EVM Description="Error vector magnitude" Control="CheckBox">1</EVM>
                <SPECMASK Description="Transmit spectrum mask" Control="CheckBox">1</SPECMASK>
                <PER Description="Receiver sensitivity" Control="CheckBox">1</PER>
                <RSSI Description="Received Signal Strength Indicator" Control="CheckBox">0</RSSI> 
                <SNR Description="Signal to Noise Ratio" Control="CheckBox">1</SNR>               
              </TestItem>
            </Group1>
          </BW_20M>
          <BW_40M Control="Group">
            <GroupCount>1</GroupCount>
            <Group1>
              <CenChan Description="Center channel 3~11 is available">3,7,11</CenChan>
              <PriChan Description="Primary channel position. 1:+10M,-1:-10M" Control="ComboBox" Elements="1,-1">1</PriChan>          
              <Modulation Control="ComboBox" Elements="HE_MCS0_1SS,HE_MCS1_1SS,HE_MCS2_1SS,HE_MCS3_1SS,HE_MCS4_1SS,HE_MCS5_1SS,HE_MCS6_1SS,HE_MCS7_1SS,HE_MCS8_1SS,HE_MCS9_1SS,HE_MCS10_1SS,HE_MCS11_1SS">HE_MCS11_1SS</Modulation>
              <RXLVL Description="Rx level for per measurement. Unit:dBm">
                <HE_MCS0_1SS>-79</HE_MCS0_1SS>
                <HE_MCS1_1SS>-76</HE_MCS1_1SS>
                <HE_MCS2_1SS>-74</HE_MCS2_1SS>
                <HE_MCS3_1SS>-71</HE_MCS3_1SS>
                <HE_MCS4_1SS>-67</HE_MCS4_1SS>
                <HE_MCS5_1SS>-63</HE_MCS5_1SS>
                <HE_MCS6_1SS>-62</HE_MCS6_1SS>
                <HE_MCS7_1SS>-61</HE_MCS7_1SS>
                <HE_MCS8_1SS>-56</HE_MCS8_1SS>
                <HE_MCS9_1SS>-54</HE_MCS9_1SS>
                <HE_MCS10_1SS>-51</HE_MCS10_1SS>
                <HE_MCS11_1SS>-49</HE_MCS11_1SS>
              </RXLVL>
              <PacketCount Description="Total packets count for RX configuration!">200</PacketCount>
              <RefLVL Description="Reference level for tx measure. Unit:dBm">20</RefLVL>
              <ChanCoding Description="Channel coding type selected: BCC, LDPC"  Control="ComboBox" Elements="0:BCC, 1:LDPC">1</ChanCoding>
              <SBW Description="Signal Bandwidth. 0:20M, 1:40M"  Control="ComboBox" Elements="0,1">1</SBW>
              <LtfModeGi Description="Set He Ltf Mode, Guard Interval"  Control="ComboBox" Elements="0:(3.2us 1x)-Gi:1(0.8us),1:(6.4us 2x)-Gi:1(0.8us),1:(6.4us 2x)-Gi:2(1.6us),2:(12.8us 4x)-Gi:1(0.8us),2:(12.8us 4x)-Gi:3(3.2us)">0:(3.2us 1x)-Gi:1(0.8us)</LtfModeGi>
              <RuSize Property ="InVisible" Description="Set Ru Size"  Control="ComboBox" Elements="26:26-RU,52:52-RU,106:106-RU,242:242-RU,484:484-RU,996:996-RU">26:26-RU</RuSize>
              <TestItem>
                <TXP Description="Transmit power level" Control="CheckBox">1</TXP>
                <TCFT Description="Transmit center frequency tolerance" Control="CheckBox">1</TCFT>
                <IQoffset Description="MODulation I/Q offset" Control="CheckBox">0</IQoffset>                
                <EVM Description="Error vector magnitude" Control="CheckBox">1</EVM>
                <SPECMASK Description="Transmit spectrum mask" Control="CheckBox">1</SPECMASK>
                <PER Description="Receiver sensitivity" Control="CheckBox">1</PER>
                <RSSI Description="Received Signal Strength Indicator" Control="CheckBox">0</RSSI>  
                <SNR Description="Signal to Noise Ratio" Control="CheckBox">1</SNR>           
              </TestItem>
            </Group1>
          </BW_40M>
          <Specification Description="Configure the test tolerance and specification">
            <TXP Description="TX Power, Unit: dBm">
              <HE_MCS0_1SS>8,23</HE_MCS0_1SS>
              <HE_MCS1_1SS>8,23</HE_MCS1_1SS>
              <HE_MCS2_1SS>8,23</HE_MCS2_1SS>
              <HE_MCS3_1SS>8,23</HE_MCS3_1SS>
              <HE_MCS4_1SS>8,23</HE_MCS4_1SS>
              <HE_MCS5_1SS>8,23</HE_MCS5_1SS>
              <HE_MCS6_1SS>8,23</HE_MCS6_1SS>
              <HE_MCS7_1SS>8,23</HE_MCS7_1SS>
              <HE_MCS8_1SS>8,23</HE_MCS8_1SS>
              <HE_MCS9_1SS>8,23</HE_MCS9_1SS>
              <HE_MCS10_1SS>8,23</HE_MCS10_1SS>
              <HE_MCS11_1SS>8,23</HE_MCS11_1SS>
            </TXP>
            <TXPant2nd Description="TX Power, Unit: dBm">
              <HE_MCS0_1SS>8,23</HE_MCS0_1SS>
              <HE_MCS1_1SS>8,23</HE_MCS1_1SS>
              <HE_MCS2_1SS>8,23</HE_MCS2_1SS>
              <HE_MCS3_1SS>8,23</HE_MCS3_1SS>
              <HE_MCS4_1SS>8,23</HE_MCS4_1SS>
              <HE_MCS5_1SS>8,23</HE_MCS5_1SS>
              <HE_MCS6_1SS>8,23</HE_MCS6_1SS>
              <HE_MCS7_1SS>8,23</HE_MCS7_1SS>
              <HE_MCS8_1SS>8,23</HE_MCS8_1SS>
              <HE_MCS9_1SS>8,23</HE_MCS9_1SS>
              <HE_MCS10_1SS>8,23</HE_MCS10_1SS>
              <HE_MCS11_1SS>8,23</HE_MCS11_1SS>
            </TXPant2nd>            
            <EVM Description="Error Vector Magnitude, Unit: %">
              <HE_MCS0_1SS>-5</HE_MCS0_1SS>
              <HE_MCS1_1SS>-10</HE_MCS1_1SS>
              <HE_MCS2_1SS>-13</HE_MCS2_1SS>
              <HE_MCS3_1SS>-16</HE_MCS3_1SS>
              <HE_MCS4_1SS>-19</HE_MCS4_1SS>
              <HE_MCS5_1SS>-22</HE_MCS5_1SS>
              <HE_MCS6_1SS>-25</HE_MCS6_1SS>
              <HE_MCS7_1SS>-28</HE_MCS7_1SS>
              <HE_MCS8_1SS>-30</HE_MCS8_1SS>
              <HE_MCS9_1SS>-32</HE_MCS9_1SS>
              <HE_MCS10_1SS>-35</HE_MCS10_1SS>
              <HE_MCS11_1SS>-35</HE_MCS11_1SS>
            </EVM>
            <SPECMASK Description="Transmit spectrum mask margin">0,0,0,0,0,0,0,0</SPECMASK>
            <TCFT Description="Transmit Center Frequency Tolerance, Unit: PPM">-15,15</TCFT>
            <IQoffset Description="MODulation I/Q offset, Unit: db">-100,-32</IQoffset>
            <PER>10</PER>
            <RSSI Description="Received Signal Strength Indicator.RXLVL+/-Limit">-4,4</RSSI>
            <SNR>10</SNR>
          </Specification>
        </Wlan11ax>
      </Band_24G>
      <Band_50G>
        <Wlan11n Description="802.11n Band">
          <BW_20M Control="Group">
            <GroupCount>1</GroupCount>
            <Group1>
              <CenChan Description="Center channel 36~64 100~144 149~161(Channel step:4) is available">36,100,149</CenChan>
              <Modulation Control="ComboBox" Elements="MCS-0,MCS-1,MCS-2,MCS-3,MCS-4,MCS-5,MCS-6,MCS-7">MCS-6</Modulation>
              <RXLVL Description="Rx level for per measurement. Unit:dBm">
                <MCS-0>-82</MCS-0>
                <MCS-1>-79</MCS-1>
                <MCS-2>-77</MCS-2>
                <MCS-3>-74</MCS-3>
                <MCS-4>-70</MCS-4>
                <MCS-5>-66</MCS-5>
                <MCS-6>-65</MCS-6>
                <MCS-7>-64</MCS-7>
              </RXLVL>
              <PacketCount Description="Total packets count for RX configuration!">200</PacketCount>
              <RefLVL Description="Reference level for tx measure. Unit:dBm">20</RefLVL>
              <ChanCoding Description="Channel coding type selected: BCC, LDPC"  Control="ComboBox" Elements="0:BCC, 1:LDPC">0</ChanCoding>
              <TestItem>
                <TXP Description="Transmit power level" Control="CheckBox">1</TXP>
                <TCFT Description="Transmit center frequency tolerance" Control="CheckBox">1</TCFT>
                <IQoffset Description="MODulation I/Q offset" Control="CheckBox">0</IQoffset>                
                <EVM Description="Error vector magnitude" Control="CheckBox">1</EVM>
                <SPECMASK Description="Transmit spectrum mask" Control="CheckBox">1</SPECMASK>
                <PER Description="Receiver sensitivity" Control="CheckBox">1</PER>
                <RSSI Description="Received Signal Strength Indicator" Control="CheckBox">0</RSSI>  
                <SNR Description="Signal to Noise Ratio" Control="CheckBox">1</SNR>      
              </TestItem>
            </Group1> 
          </BW_20M>
          <BW_40M Control="Group">
            <GroupCount>1</GroupCount>
            <Group1>
              <CenChan Description="Center channel 38~62 102~142 151~159 (channel step:8) is available">38,102,151</CenChan>
              <PriChan Description="Primary channel position. 1:+10M,0:0,-1:-10M" Control="ComboBox" Elements="1,-1">1</PriChan>
              <Modulation Control="ComboBox" Elements="MCS-0,MCS-1,MCS-2,MCS-3,MCS-4,MCS-5,MCS-6,MCS-7">MCS-7</Modulation>
              <RXLVL Description="Rx level for per measurement. Unit:dBm">
                <MCS-0>-79</MCS-0>
                <MCS-1>-76</MCS-1>
                <MCS-2>-74</MCS-2>
                <MCS-3>-71</MCS-3>
                <MCS-4>-67</MCS-4>
                <MCS-5>-63</MCS-5>
                <MCS-6>-62</MCS-6>
                <MCS-7>-61</MCS-7>
              </RXLVL>
              <PacketCount Description="Total packets count for RX configuration!">200</PacketCount>
              <RefLVL Description="Reference level for tx measure. Unit:dBm">20</RefLVL>
              <ChanCoding Description="Channel coding type selected: BCC, LDPC"  Control="ComboBox" Elements="0:BCC, 1:LDPC">0</ChanCoding>
              <SBW Property="ReadOnly" Description="Signal Bandwidth. 0:20M, 1:40M"  Control="ComboBox" Elements="0,1">1</SBW>
              <TestItem>
                <TXP Description="Transmit power level" Control="CheckBox">1</TXP>
                <TCFT Description="Transmit center frequency tolerance" Control="CheckBox">1</TCFT>
                <IQoffset Description="MODulation I/Q offset" Control="CheckBox">0</IQoffset>                
                <EVM Description="Error vector magnitude" Control="CheckBox">1</EVM>
                <SPECMASK Description="Transmit spectrum mask" Control="CheckBox">1</SPECMASK>
                <PER Description="Receiver sensitivity" Control="CheckBox">1</PER>
                <RSSI Description="Received Signal Strength Indicator" Control="CheckBox">0</RSSI>  
                <SNR Description="Signal to Noise Ratio" Control="CheckBox">1</SNR>            
              </TestItem>
            </Group1>
          </BW_40M>
          <Specification Description="Configure the test tolerance and specification">
            <TXP Description="TX Power, Unit: dBm">
              <MCS-0>8,23</MCS-0>
              <MCS-1>8,23</MCS-1>
              <MCS-2>8,23</MCS-2>
              <MCS-3>8,23</MCS-3>
              <MCS-4>8,23</MCS-4>
              <MCS-5>8,23</MCS-5>
              <MCS-6>8,23</MCS-6>
              <MCS-7>8,23</MCS-7>
            </TXP>
            <TXPant2nd Description="TX Power, Unit: dBm">
              <MCS-0>8,23</MCS-0>
              <MCS-1>8,23</MCS-1>
              <MCS-2>8,23</MCS-2>
              <MCS-3>8,23</MCS-3>
              <MCS-4>8,23</MCS-4>
              <MCS-5>8,23</MCS-5>
              <MCS-6>8,23</MCS-6>
              <MCS-7>8,23</MCS-7>
            </TXPant2nd>            
            <EVM Description="Error Vector Magnitude, Unit: %">
              <MCS-0>-5</MCS-0>
              <MCS-1>-10</MCS-1>
              <MCS-2>-13</MCS-2>
              <MCS-3>-16</MCS-3>
              <MCS-4>-19</MCS-4>
              <MCS-5>-22</MCS-5>
              <MCS-6>-25</MCS-6>
              <MCS-7>-28</MCS-7>
            </EVM>
            <SPECMASK Description="Transmit spectrum mask margin">0,0,0,0,0,0,0,0</SPECMASK>
            <TCFT Description="Transmit Center Frequency Tolerance, Unit: PPM">-15,15</TCFT>
            <IQoffset Description="MODulation I/Q offset, Unit: db">-100,-20</IQoffset>
            <PER>10</PER>
            <RSSI Description="Received Signal Strength Indicator.RXLVL+/-Limit">-4,4</RSSI>
            <SNR>10</SNR>
          </Specification>
        </Wlan11n>
        <Wlan11ac Description="802.11ac Band" Control="Group">
            <BW_20M Control="Group">
              <GroupCount>1</GroupCount>
              <Group1>
                <CenChan Description="Center channel 36~64 100~144 149~161(Channel step:4) is available">36,100,149</CenChan>
                <Modulation Control="ComboBox" Elements="MCS0_1SS,MCS1_1SS,MCS2_1SS,MCS3_1SS,MCS4_1SS,MCS5_1SS,MCS6_1SS,MCS7_1SS,MCS8_1SS">MCS7_1SS</Modulation>
                <RXLVL Description="Rx level for per measurement. Unit:dBm">
                  <MCS0_1SS>-82</MCS0_1SS>
                  <MCS1_1SS>-79</MCS1_1SS>
                  <MCS2_1SS>-77</MCS2_1SS>
                  <MCS3_1SS>-74</MCS3_1SS>
                  <MCS4_1SS>-70</MCS4_1SS>
                  <MCS5_1SS>-66</MCS5_1SS>
                  <MCS6_1SS>-65</MCS6_1SS>
                  <MCS7_1SS>-64</MCS7_1SS>
                  <MCS8_1SS>-59</MCS8_1SS>
                  <MCS9_1SS>-57</MCS9_1SS>
                </RXLVL>
                <PacketCount Description="Total packets count for RX configuration!">200</PacketCount>
                <RefLVL Description="Reference level for tx measure. Unit:dBm">20</RefLVL>
                <ChanCoding Description="Channel coding type selected: BCC, LDPC"  Control="ComboBox" Elements="0:BCC, 1:LDPC">0</ChanCoding>
                <TestItem>
                      <TXP Description="Transmit power level" Control="CheckBox">1</TXP>
                      <TCFT Description="Transmit center frequency tolerance" Control="CheckBox">1</TCFT>
                      <IQoffset Description="MODulation I/Q offset" Control="CheckBox">0</IQoffset>                  
                      <EVM Description="Error vector magnitude" Control="CheckBox">1</EVM>
                      <SPECMASK Description="Transmit spectrum mask" Control="CheckBox">1</SPECMASK>
                      <PER Description="Receiver sensitivity" Control="CheckBox">1</PER>
                      <RSSI Description="Received Signal Strength Indicator" Control="CheckBox">0</RSSI> 
                      <SNR Description="Signal to Noise Ratio" Control="CheckBox">1</SNR>               
                  </TestItem>
              </Group1>
            </BW_20M>
            <BW_40M Control="Group">
              <GroupCount>1</GroupCount>
              <Group1>
                <CenChan Description="Center channel 38~62 102~142 151~159 (channel step:8) is available">38,102,151</CenChan>
                <PriChan Description="Primary channel position. 1:+10M,0:0,-1:-10M" Control="ComboBox" Elements="1,-1">1</PriChan>
                <Modulation Control="ComboBox" Elements="MCS0_1SS,MCS1_1SS,MCS2_1SS,MCS3_1SS,MCS4_1SS,MCS5_1SS,MCS6_1SS,MCS7_1SS,MCS8_1SS,MCS9_1SS">MCS8_1SS</Modulation>
                <RXLVL Description="Rx level for per measurement. Unit:dBm">
                  <MCS0_1SS>-79</MCS0_1SS>
                  <MCS1_1SS>-76</MCS1_1SS>
                  <MCS2_1SS>-74</MCS2_1SS>
                  <MCS3_1SS>-71</MCS3_1SS>
                  <MCS4_1SS>-67</MCS4_1SS>
                  <MCS5_1SS>-63</MCS5_1SS>
                  <MCS6_1SS>-62</MCS6_1SS>
                  <MCS7_1SS>-61</MCS7_1SS>
                  <MCS8_1SS>-56</MCS8_1SS>
                  <MCS9_1SS>-54</MCS9_1SS>
                </RXLVL>
                <PacketCount Description="Total packets count for RX configuration!">200</PacketCount>
                <RefLVL Description="Reference level for tx measure. Unit:dBm">20</RefLVL>
                <ChanCoding Description="Channel coding type selected: BCC, LDPC"  Control="ComboBox" Elements="0:BCC, 1:LDPC">0</ChanCoding>
                <SBW Description="Signal Bandwidth. 0:20M, 1:40M"  Control="ComboBox" Elements="0,1">1</SBW>
                <TestItem>
                  <TXP Description="Transmit power level" Control="CheckBox">1</TXP>
                  <TCFT Description="Transmit center frequency tolerance" Control="CheckBox">1</TCFT>
                  <IQoffset Description="MODulation I/Q offset" Control="CheckBox">0</IQoffset>                  
                  <EVM Description="Error vector magnitude" Control="CheckBox">1</EVM>
                  <SPECMASK Description="Transmit spectrum mask" Control="CheckBox">1</SPECMASK>
                  <PER Description="Receiver sensitivity" Control="CheckBox">1</PER>
                  <RSSI Description="Received Signal Strength Indicator" Control="CheckBox">0</RSSI>   
                  <SNR Description="Signal to Noise Ratio" Control="CheckBox">1</SNR>             
                </TestItem>
              </Group1>
            </BW_40M>
           <BW_80M Control="Group">
              <GroupCount>1</GroupCount>
              <Group1>
                <CenChan Description="Center channel 42,58,106,122,138,155 is available">42,106,155</CenChan>
                <PriChan Description="Primary channel position. 3:+30M,1:+10M,0:0,-1:-10M,-3:-30M" Control="ComboBox" Elements="3,1,-1,-3">1</PriChan>
                <Modulation Control="ComboBox" Elements="MCS0_1SS,MCS1_1SS,MCS2_1SS,MCS3_1SS,MCS4_1SS,MCS5_1SS,MCS6_1SS,MCS7_1SS,MCS8_1SS,MCS9_1SS">MCS9_1SS</Modulation>
                <RXLVL Description="Rx level for per measurement. Unit:dBm">
                  <MCS0_1SS>-76</MCS0_1SS>
                  <MCS1_1SS>-73</MCS1_1SS>
                  <MCS2_1SS>-71</MCS2_1SS>
                  <MCS3_1SS>-68</MCS3_1SS>
                  <MCS4_1SS>-64</MCS4_1SS>
                  <MCS5_1SS>-60</MCS5_1SS>
                  <MCS6_1SS>-59</MCS6_1SS>
                  <MCS7_1SS>-58</MCS7_1SS>
                  <MCS8_1SS>-53</MCS8_1SS>
                  <MCS9_1SS>-51</MCS9_1SS>
                </RXLVL>
                <PacketCount Description="Total packets count for RX configuration!">200</PacketCount>
                <RefLVL Description="Reference level for tx measure. Unit:dBm">20</RefLVL>
                <ChanCoding Description="Channel coding type selected: BCC, LDPC"  Control="ComboBox" Elements="0:BCC, 1:LDPC">0</ChanCoding>
                <SBW Description="Signal Bandwidth. 0:20M, 1:40M, 2:80M"  Control="ComboBox" Elements="0,1,2">2</SBW>
                <TestItem>
                  <TXP Description="Transmit power level" Control="CheckBox">1</TXP>
                  <TCFT Description="Transmit center frequency tolerance" Control="CheckBox">1</TCFT>
                  <IQoffset Description="MODulation I/Q offset" Control="CheckBox">0</IQoffset>                  
                  <EVM Description="Error vector magnitude" Control="CheckBox">1</EVM>
                  <SPECMASK Description="Transmit spectrum mask" Control="CheckBox">1</SPECMASK>
                  <PER Description="Receiver sensitivity" Control="CheckBox">1</PER>
                  <RSSI Description="Received Signal Strength Indicator" Control="CheckBox">0</RSSI> 
                  <SNR Description="Signal to Noise Ratio" Control="CheckBox">1</SNR>      
                </TestItem>
              </Group1>
            </BW_80M>
          <Specification Description="Configure the test tolerance and specification">
            <TXP Description="TX Power, Unit: dBm">
              <MCS0_1SS>8,23</MCS0_1SS>
              <MCS1_1SS>8,23</MCS1_1SS>
              <MCS2_1SS>8,23</MCS2_1SS>
              <MCS3_1SS>8,23</MCS3_1SS>
              <MCS4_1SS>8,23</MCS4_1SS>
              <MCS5_1SS>8,23</MCS5_1SS>
              <MCS6_1SS>8,23</MCS6_1SS>
              <MCS7_1SS>8,23</MCS7_1SS>
              <MCS8_1SS>8,23</MCS8_1SS>
              <MCS9_1SS>8,23</MCS9_1SS>
            </TXP>
            <TXPant2nd Description="TX Power, Unit: dBm">
              <MCS0_1SS>8,23</MCS0_1SS>
              <MCS1_1SS>8,23</MCS1_1SS>
              <MCS2_1SS>8,23</MCS2_1SS>
              <MCS3_1SS>8,23</MCS3_1SS>
              <MCS4_1SS>8,23</MCS4_1SS>
              <MCS5_1SS>8,23</MCS5_1SS>
              <MCS6_1SS>8,23</MCS6_1SS>
              <MCS7_1SS>8,23</MCS7_1SS>
              <MCS8_1SS>8,23</MCS8_1SS>
              <MCS9_1SS>8,23</MCS9_1SS>
            </TXPant2nd>            
            <EVM Description="Error Vector Magnitude, Unit: %">
              <MCS0_1SS>-5</MCS0_1SS>
              <MCS1_1SS>-10</MCS1_1SS>
              <MCS2_1SS>-13</MCS2_1SS>
              <MCS3_1SS>-16</MCS3_1SS>
              <MCS4_1SS>-19</MCS4_1SS>
              <MCS5_1SS>-22</MCS5_1SS>
              <MCS6_1SS>-25</MCS6_1SS>
              <MCS7_1SS>-28</MCS7_1SS>
              <MCS8_1SS>-30</MCS8_1SS>
              <MCS9_1SS>-32</MCS9_1SS>
            </EVM>
            <SPECMASK Description="Transmit spectrum mask margin">0,0,0,0,0,0,0,0</SPECMASK>
            <TCFT Description="Transmit Center Frequency Tolerance, Unit: PPM">-15,15</TCFT>
            <IQoffset Description="MODulation I/Q offset, Unit: db">-100,-24</IQoffset>
            <PER>10</PER>
            <RSSI Description="Received Signal Strength Indicator.RXLVL+/-Limit">-4,4</RSSI>
            <SNR>10</SNR>
          </Specification>
      </Wlan11ac>
        <Wlan11a Description="802.11a Band" Control="Group">
          <BW_20M Control="Group">
            <GroupCount>1</GroupCount>
            <Group1>
              <CenChan Description="Center channel 36~64 100~144 149~161(Channel step:4) is available">36,100,149</CenChan>
              <Modulation Control="ComboBox" Elements="OFDM-6,OFDM-9,OFDM-12,OFDM-18,OFDM-24,OFDM-36,OFDM-48,OFDM-54">OFDM-54</Modulation>
              <RXLVL Description="Rx level for per measurement. Unit:dBm">
                <OFDM-6>-82</OFDM-6>
                <OFDM-9>-81</OFDM-9>
                <OFDM-12>-79</OFDM-12>
                <OFDM-18>-77</OFDM-18>
                <OFDM-24>-74</OFDM-24>
                <OFDM-36>-70</OFDM-36>
                <OFDM-48>-66</OFDM-48>
                <OFDM-54>-65</OFDM-54>
              </RXLVL>
              <PacketCount Description="Total packets count for RX configuration!">200</PacketCount>
              <RefLVL Description="Reference level for tx measure. Unit:dBm">20</RefLVL>
              <ChanCoding Description="Channel coding type selected: BCC, LDPC"  Control="ComboBox" Elements="0:BCC, 1:LDPC">0</ChanCoding>
              <TestItem>
                <TXP Description="Transmit power level" Control="CheckBox">1</TXP>
                <TCFT Description="Transmit center frequency tolerance" Control="CheckBox">1</TCFT>
                <IQoffset Description="MODulation I/Q offset" Control="CheckBox">0</IQoffset>                
                <EVM Description="Error vector magnitude" Control="CheckBox">1</EVM>
                <SPECMASK Description="Transmit spectrum mask" Control="CheckBox">1</SPECMASK>
                <PER Description="Receiver sensitivity" Control="CheckBox">1</PER>
                <RSSI Description="Received Signal Strength Indicator" Control="CheckBox">0</RSSI> 
                <SNR Description="Signal to Noise Ratio" Control="CheckBox">1</SNR>        
              </TestItem>
            </Group1>
          </BW_20M>
          <Specification Description="Configure the test tolerance and specification">
            <TXP Description="TX Power, Unit: dBm">
              <OFDM-6>8,23</OFDM-6>
              <OFDM-9>8,23</OFDM-9>
              <OFDM-12>8,23</OFDM-12>
              <OFDM-18>8,23</OFDM-18>
              <OFDM-24>8,23</OFDM-24>
              <OFDM-36>8,23</OFDM-36>
              <OFDM-48>8,23</OFDM-48>
              <OFDM-54>8,23</OFDM-54>
            </TXP>
            <TXPant2nd Description="TX Power, Unit: dBm">
              <OFDM-6>8,23</OFDM-6>
              <OFDM-9>8,23</OFDM-9>
              <OFDM-12>8,23</OFDM-12>
              <OFDM-18>8,23</OFDM-18>
              <OFDM-24>8,23</OFDM-24>
              <OFDM-36>8,23</OFDM-36>
              <OFDM-48>8,23</OFDM-48>
              <OFDM-54>8,23</OFDM-54>
            </TXPant2nd>            
            <TCFT Description="Transmit Center Freq Tolerance, Unit: PPM">-15,15</TCFT>
            <IQoffset Description="MODulation I/Q offset, Unit: db">-100,-15</IQoffset>
            <EVM Description="Error Vector Magnitude, Unit: %">
              <OFDM-6>-5</OFDM-6>
              <OFDM-9>-8</OFDM-9>
              <OFDM-12>-10</OFDM-12>
              <OFDM-18>-13</OFDM-18>
              <OFDM-24>-16</OFDM-24>
              <OFDM-36>-19</OFDM-36>
              <OFDM-48>-22</OFDM-48>
              <OFDM-54>-25</OFDM-54>
            </EVM>
            <SPECMASK Description="Transmit spectrum mask margin">0,0,0,0,0,0,0,0</SPECMASK>
            <PER>10</PER>
            <RSSI Description="Received Signal Strength Indicator.RXLVL+/-Limit">-4,4</RSSI>    
            <SNR>10</SNR>       
          </Specification>
        </Wlan11a>
        <Wlan11ax Description="802.11ax Band" Control="Group">
            <BW_20M Control="Group">
              <GroupCount>1</GroupCount>
              <Group1>
                <CenChan Description="Center channel 36~64 100~144 149~161(Channel step:4) is available">36,100,149</CenChan>
                <Modulation Control="ComboBox" Elements="HE_MCS0_1SS,HE_MCS1_1SS,HE_MCS2_1SS,HE_MCS3_1SS,HE_MCS4_1SS,HE_MCS5_1SS,HE_MCS6_1SS,HE_MCS7_1SS,HE_MCS8_1SS,HE_MCS9_1SS,HE_MCS10_1SS,HE_MCS11_1SS">HE_MCS9_1SS</Modulation>
                <RXLVL Description="Rx level for per measurement. Unit:dBm">
                  <HE_MCS0_1SS>-82</HE_MCS0_1SS>
                  <HE_MCS1_1SS>-79</HE_MCS1_1SS>
                  <HE_MCS2_1SS>-77</HE_MCS2_1SS>
                  <HE_MCS3_1SS>-74</HE_MCS3_1SS>
                  <HE_MCS4_1SS>-70</HE_MCS4_1SS>
                  <HE_MCS5_1SS>-66</HE_MCS5_1SS>
                  <HE_MCS6_1SS>-65</HE_MCS6_1SS>
                  <HE_MCS7_1SS>-64</HE_MCS7_1SS>
                  <HE_MCS8_1SS>-59</HE_MCS8_1SS>
                  <HE_MCS9_1SS>-57</HE_MCS9_1SS>
                  <HE_MCS10_1SS>-54</HE_MCS10_1SS>
                  <HE_MCS11_1SS>-52</HE_MCS11_1SS>
                </RXLVL>
                <PacketCount Description="Total packets count for RX configuration!">200</PacketCount>
                <RefLVL Description="Reference level for tx measure. Unit:dBm">20</RefLVL>
                <ChanCoding Description="Channel coding type selected: BCC, LDPC"  Control="ComboBox" Elements="0:BCC, 1:LDPC">1</ChanCoding>
                <LtfModeGi Description="Set He Ltf Mode, Guard Interval"  Control="ComboBox" Elements="0:(3.2us 1x)-Gi:1(0.8us),1:(6.4us 2x)-Gi:1(0.8us),1:(6.4us 2x)-Gi:2(1.6us),2:(12.8us 4x)-Gi:1(0.8us),2:(12.8us 4x)-Gi:3(3.2us)">0:(3.2us 1x)-Gi:1(0.8us)</LtfModeGi>
                <RuSize Property ="InVisible" Description="Set Ru Size"  Control="ComboBox" Elements="26:26-RU,52:52-RU,106:106-RU,242:242-RU,484:484-RU,996:996-RU">26:26-RU</RuSize>
                <TestItem>
                      <TXP Description="Transmit power level" Control="CheckBox">1</TXP>
                      <TCFT Description="Transmit center frequency tolerance" Control="CheckBox">1</TCFT>
                      <IQoffset Description="MODulation I/Q offset" Control="CheckBox">0</IQoffset>                  
                      <EVM Description="Error vector magnitude" Control="CheckBox">1</EVM>
                      <SPECMASK Description="Transmit spectrum mask" Control="CheckBox">1</SPECMASK>
                      <PER Description="Receiver sensitivity" Control="CheckBox">1</PER>
                      <RSSI Description="Received Signal Strength Indicator" Control="CheckBox">0</RSSI> 
                      <SNR Description="Signal to Noise Ratio" Control="CheckBox">1</SNR>               
                  </TestItem>
              </Group1>
            </BW_20M>
            <BW_40M Control="Group">
              <GroupCount>1</GroupCount>
              <Group1>
                <CenChan Description="Center channel 38~62 102~142 151~159 (channel step:8) is available">38,102,151</CenChan>
                <PriChan Description="Primary channel position. 1:+10M,0:0,-1:-10M" Control="ComboBox" Elements="1,-1">1</PriChan>            
                <Modulation Control="ComboBox" Elements="HE_MCS0_1SS,HE_MCS1_1SS,HE_MCS2_1SS,HE_MCS3_1SS,HE_MCS4_1SS,HE_MCS5_1SS,HE_MCS6_1SS,HE_MCS7_1SS,HE_MCS8_1SS,HE_MCS9_1SS,HE_MCS10_1SS,HE_MCS11_1SS">HE_MCS10_1SS</Modulation>
                <RXLVL Description="Rx level for per measurement. Unit:dBm">
                  <HE_MCS0_1SS>-79</HE_MCS0_1SS>
                  <HE_MCS1_1SS>-76</HE_MCS1_1SS>
                  <HE_MCS2_1SS>-74</HE_MCS2_1SS>
                  <HE_MCS3_1SS>-71</HE_MCS3_1SS>
                  <HE_MCS4_1SS>-67</HE_MCS4_1SS>
                  <HE_MCS5_1SS>-63</HE_MCS5_1SS>
                  <HE_MCS6_1SS>-62</HE_MCS6_1SS>
                  <HE_MCS7_1SS>-61</HE_MCS7_1SS>
                  <HE_MCS8_1SS>-56</HE_MCS8_1SS>
                  <HE_MCS9_1SS>-54</HE_MCS9_1SS>
                  <HE_MCS10_1SS>-51</HE_MCS10_1SS>
                  <HE_MCS11_1SS>-49</HE_MCS11_1SS>
                </RXLVL>
                <PacketCount Description="Total packets count for RX configuration!">200</PacketCount>
                <RefLVL Description="Reference level for tx measure. Unit:dBm">20</RefLVL>
                <ChanCoding Description="Channel coding type selected: BCC, LDPC"  Control="ComboBox" Elements="0:BCC, 1:LDPC">1</ChanCoding>
                <SBW Description="Signal Bandwidth. 0:20M, 1:40M"  Control="ComboBox" Elements="0,1">1</SBW>
                <LtfModeGi Description="Set He Ltf Mode, Guard Interval"  Control="ComboBox" Elements="0:(3.2us 1x)-Gi:1(0.8us),1:(6.4us 2x)-Gi:1(0.8us),1:(6.4us 2x)-Gi:2(1.6us),2:(12.8us 4x)-Gi:1(0.8us),2:(12.8us 4x)-Gi:3(3.2us)">0:(3.2us 1x)-Gi:1(0.8us)</LtfModeGi>
                <RuSize Property ="InVisible" Description="Set Ru Size"  Control="ComboBox" Elements="26:26-RU,52:52-RU,106:106-RU,242:242-RU,484:484-RU,996:996-RU">26:26-RU</RuSize>
                <TestItem>
                  <TXP Description="Transmit power level" Control="CheckBox">1</TXP>
                  <TCFT Description="Transmit center frequency tolerance" Control="CheckBox">1</TCFT>
                  <IQoffset Description="MODulation I/Q offset" Control="CheckBox">0</IQoffset>                  
                  <EVM Description="Error vector magnitude" Control="CheckBox">1</EVM>
                  <SPECMASK Description="Transmit spectrum mask" Control="CheckBox">1</SPECMASK>
                  <PER Description="Receiver sensitivity" Control="CheckBox">1</PER>
                  <RSSI Description="Received Signal Strength Indicator" Control="CheckBox">0</RSSI>  
                  <SNR Description="Signal to Noise Ratio" Control="CheckBox">1</SNR>            
                </TestItem>
              </Group1>
            </BW_40M>
           <BW_80M Control="Group">
              <GroupCount>1</GroupCount>
              <Group1>
                <CenChan Description="Center channel 42,58,106,122,138,155 is available">42,106,155</CenChan>
                <PriChan Description="Primary channel position. 3:+30M,1:+10M,0:0,-1:-10M,-3:-30M" Control="ComboBox" Elements="3,1,-1,-3">1</PriChan>
                <Modulation Control="ComboBox" Elements="HE_MCS0_1SS,HE_MCS1_1SS,HE_MCS2_1SS,HE_MCS3_1SS,HE_MCS4_1SS,HE_MCS5_1SS,HE_MCS6_1SS,HE_MCS7_1SS,HE_MCS8_1SS,HE_MCS9_1SS,HE_MCS10_1SS,HE_MCS11_1SS">HE_MCS11_1SS</Modulation>
                <RXLVL Description="Rx level for per measurement. Unit:dBm">
                  <HE_MCS0_1SS>-76</HE_MCS0_1SS>
                  <HE_MCS1_1SS>-73</HE_MCS1_1SS>
                  <HE_MCS2_1SS>-71</HE_MCS2_1SS>
                  <HE_MCS3_1SS>-68</HE_MCS3_1SS>
                  <HE_MCS4_1SS>-64</HE_MCS4_1SS>
                  <HE_MCS5_1SS>-60</HE_MCS5_1SS>
                  <HE_MCS6_1SS>-59</HE_MCS6_1SS>
                  <HE_MCS7_1SS>-58</HE_MCS7_1SS>
                  <HE_MCS8_1SS>-53</HE_MCS8_1SS>
                  <HE_MCS9_1SS>-51</HE_MCS9_1SS>
                  <HE_MCS10_1SS>-48</HE_MCS10_1SS>
                  <HE_MCS11_1SS>-46</HE_MCS11_1SS>
                </RXLVL>
                <PacketCount Description="Total packets count for RX configuration!">200</PacketCount>
                <RefLVL Description="Reference level for tx measure. Unit:dBm">20</RefLVL>
                <ChanCoding Description="Channel coding type selected: BCC, LDPC"  Control="ComboBox" Elements="0:BCC, 1:LDPC">1</ChanCoding>
                <SBW Description="Signal Bandwidth. 0:20M, 1:40M, 2:80M"  Control="ComboBox" Elements="0,1,2">2</SBW>
                <LtfModeGi Description="Set He Ltf Mode, Guard Interval"  Control="ComboBox" Elements="0:(3.2us 1x)-Gi:1(0.8us),1:(6.4us 2x)-Gi:1(0.8us),1:(6.4us 2x)-Gi:2(1.6us),2:(12.8us 4x)-Gi:1(0.8us),2:(12.8us 4x)-Gi:3(3.2us)">0:(3.2us 1x)-Gi:1(0.8us)</LtfModeGi>
                <RuSize Property ="InVisible" Description="Set Ru Size"  Control="ComboBox" Elements="26:26-RU,52:52-RU,106:106-RU,242:242-RU,484:484-RU,996:996-RU">26:26-RU</RuSize>
                <TestItem>
                  <TXP Description="Transmit power level" Control="CheckBox">1</TXP>
                  <TCFT Description="Transmit center frequency tolerance" Control="CheckBox">1</TCFT>
                  <IQoffset Description="MODulation I/Q offset" Control="CheckBox">0</IQoffset>                  
                  <EVM Description="Error vector magnitude" Control="CheckBox">1</EVM>
                  <SPECMASK Description="Transmit spectrum mask" Control="CheckBox">1</SPECMASK>
                  <PER Description="Receiver sensitivity" Control="CheckBox">1</PER>
                  <RSSI Description="Received Signal Strength Indicator" Control="CheckBox">0</RSSI>   
                  <SNR Description="Signal to Noise Ratio" Control="CheckBox">1</SNR>               
                </TestItem>
              </Group1>
            </BW_80M>
           <!--BW_160M Control="Group">
              <GroupCount>1</GroupCount>
              <Group1>
                <CenChan Description="Center channel 36~64(~Channel step:4) is available">36,48,64</CenChan>
                <PriChan Description="Primary channel position. 7:+70M,-7:-70M" Control="ComboBox" Elements="7,-7">7</PriChan>
                <Modulation Control="ComboBox" Elements="HE_MCS0_1SS,HE_MCS1_1SS,HE_MCS2_1SS,HE_MCS3_1SS,HE_MCS4_1SS,HE_MCS5_1SS,HE_MCS6_1SS,HE_MCS7_1SS,HE_MCS8_1SS,HE_MCS9_1SS,HE_MCS10_1SS,HE_MCS11_1SS">HE_MCS11_1SS</Modulation>
                <RXLVL Description="Rx level for per measurement. Unit:dBm">
                  <HE_MCS0_1SS>-73</HE_MCS0_1SS>
                  <HE_MCS1_1SS>-70</HE_MCS1_1SS>
                  <HE_MCS2_1SS>-68</HE_MCS2_1SS>
                  <HE_MCS3_1SS>-65</HE_MCS3_1SS>
                  <HE_MCS4_1SS>-61</HE_MCS4_1SS>
                  <HE_MCS5_1SS>-57</HE_MCS5_1SS>
                  <HE_MCS6_1SS>-56</HE_MCS6_1SS>
                  <HE_MCS7_1SS>-55</HE_MCS7_1SS>
                  <HE_MCS8_1SS>-50</HE_MCS8_1SS>
                  <HE_MCS9_1SS>-48</HE_MCS9_1SS>
                  <HE_MCS10_1SS>-45</HE_MCS10_1SS>
                  <HE_MCS11_1SS>-43</HE_MCS11_1SS>
                </RXLVL>
                <PacketCount Description="Total packets count for RX configuration!">200</PacketCount>
                <RefLVL Description="Reference level for tx measure. Unit:dBm">20</RefLVL>
                <ChanCoding Description="Channel coding type selected: BCC, LDPC"  Control="ComboBox" Elements="0:BCC, 1:LDPC">1</ChanCoding>
                <SBW Description="Signal Bandwidth. 0:20M, 1:40M, 2:80M, 3:160M"  Control="ComboBox" Elements="0,1,2,3">3</SBW>
                <LtfModeGi Description="Set He Ltf Mode, Guard Interval"  Control="ComboBox" Elements="0:(3.2us 1x)-Gi:1(0.8us),1:(6.4us 2x)-Gi:1(0.8us),1:(6.4us 2x)-Gi:2(1.6us),2:(12.8us 4x)-Gi:1(0.8us),2:(12.8us 4x)-Gi:3(3.2us)">0:(3.2us 1x)-Gi:1(0.8us)</LtfModeGi>
                <RuSize Property ="InVisible" Description="Set Ru Size"  Control="ComboBox" Elements="26:26-RU,52:52-RU,106:106-RU,242:242-RU,484:484-RU,996:996-RU">26:26-RU</RuSize>
                <TestItem>
                  <TXP Description="Transmit power level" Control="CheckBox">1</TXP>
                  <TCFT Description="Transmit center frequency tolerance" Control="CheckBox">1</TCFT>
                  <IQoffset Description="MODulation I/Q offset" Control="CheckBox">0</IQoffset>                  
                  <EVM Description="Error vector magnitude" Control="CheckBox">1</EVM>
                  <SPECMASK Description="Transmit spectrum mask" Control="CheckBox">1</SPECMASK>
                  <PER Description="Receiver sensitivity" Control="CheckBox">1</PER>
                  <RSSI Description="Received Signal Strength Indicator" Control="CheckBox">0</RSSI>   
                  <SNR Description="Signal to Noise Ratio" Control="CheckBox">1</SNR>             
                </TestItem>
              </Group1>
            </BW_160M-->			
          <Specification Description="Configure the test tolerance and specification">
            <TXP Description="TX Power, Unit: dBm">
              <HE_MCS0_1SS>8,23</HE_MCS0_1SS>
              <HE_MCS1_1SS>8,23</HE_MCS1_1SS>
              <HE_MCS2_1SS>8,23</HE_MCS2_1SS>
              <HE_MCS3_1SS>8,23</HE_MCS3_1SS>
              <HE_MCS4_1SS>8,23</HE_MCS4_1SS>
              <HE_MCS5_1SS>8,23</HE_MCS5_1SS>
              <HE_MCS6_1SS>8,23</HE_MCS6_1SS>
              <HE_MCS7_1SS>8,23</HE_MCS7_1SS>
              <HE_MCS8_1SS>8,23</HE_MCS8_1SS>
              <HE_MCS9_1SS>8,23</HE_MCS9_1SS>
              <HE_MCS10_1SS>8,23</HE_MCS10_1SS>
              <HE_MCS11_1SS>8,23</HE_MCS11_1SS>
            </TXP>
            <TXPant2nd Description="TX Power, Unit: dBm">
              <HE_MCS0_1SS>8,23</HE_MCS0_1SS>
              <HE_MCS1_1SS>8,23</HE_MCS1_1SS>
              <HE_MCS2_1SS>8,23</HE_MCS2_1SS>
              <HE_MCS3_1SS>8,23</HE_MCS3_1SS>
              <HE_MCS4_1SS>8,23</HE_MCS4_1SS>
              <HE_MCS5_1SS>8,23</HE_MCS5_1SS>
              <HE_MCS6_1SS>8,23</HE_MCS6_1SS>
              <HE_MCS7_1SS>8,23</HE_MCS7_1SS>
              <HE_MCS8_1SS>8,23</HE_MCS8_1SS>
              <HE_MCS9_1SS>8,23</HE_MCS9_1SS>
              <HE_MCS10_1SS>8,23</HE_MCS10_1SS>
              <HE_MCS11_1SS>8,23</HE_MCS11_1SS>
            </TXPant2nd>
            <EVM Description="Error Vector Magnitude, Unit: %">
              <HE_MCS0_1SS>-5</HE_MCS0_1SS>
              <HE_MCS1_1SS>-10</HE_MCS1_1SS>
              <HE_MCS2_1SS>-13</HE_MCS2_1SS>
              <HE_MCS3_1SS>-16</HE_MCS3_1SS>
              <HE_MCS4_1SS>-19</HE_MCS4_1SS>
              <HE_MCS5_1SS>-22</HE_MCS5_1SS>
              <HE_MCS6_1SS>-25</HE_MCS6_1SS>
              <HE_MCS7_1SS>-28</HE_MCS7_1SS>
              <HE_MCS8_1SS>-30</HE_MCS8_1SS>
              <HE_MCS9_1SS>-32</HE_MCS9_1SS>
              <HE_MCS10_1SS>-35</HE_MCS10_1SS>
              <HE_MCS11_1SS>-35</HE_MCS11_1SS>
            </EVM>
            <SPECMASK Description="Transmit spectrum mask margin">0,0,0,0,0,0,0,0</SPECMASK>
            <TCFT Description="Transmit Center Frequency Tolerance, Unit: PPM">-15,15</TCFT>
            <IQoffset Description="MODulation I/Q offset, Unit: db">-100,-32</IQoffset>
            <PER>10</PER>
            <RSSI Description="Received Signal Strength Indicator.RXLVL+/-Limit">-4,4</RSSI>
            <SNR>10</SNR>
          </Specification>
      </Wlan11ax>		
      </Band_50G>
    </Param>
</Node>
